[
  {
    "user": "คุณกิตติศักดิ์",
    "rating": 5,
    "comment": "บะหมี่เส้นนุ่มมากครับ เกี๊ยวปูให้เนื้อมาเป็นก้อนๆ เลย หมูแดงก็หอมกลิ่นย่างเตาถ่านมาก แนะนำให้มาลองครับ",
    "date": "2024-11-15"
  },
  {
    "user": "เจ๊หมวย สายกิน",
    "rating": 5,
    "comment": "ร้านสะอาดมากค่ะ เฮียเนกกับเจ๊ตั๊กบริการเป็นกันเองสุดๆ ชอบบะหมี่ต้มยำแห้ง รสชาติจัดจ้านไม่ต้องปรุงเพิ่มเลย",
    "date": "2024-11-20"
  },
  {
    "user": "Tanakorn P.",
    "rating": 4,
    "comment": "เป็นร้านประจำเวลามาทำธุระที่จ.ตาก เลยครับ รสชาติคงที่มาก ทานมาหลายปีคุณภาพไม่เคยเปลี่ยน",
    "date": "2024-12-01"
  },
  {
    "user": "น้องแพร รีวิว",
    "rating": 5,
    "comment": "เกี๊ยวกุ้งคำโตสะใจมากค่ะ น้ำซุปเชงๆ ซดคล่องคอ อิ่มอร่อยคุ้มค่าราคามากค่ะ",
    "date": "2024-12-10"
  },
  {
    "user": "พี่อาร์ต คนรักเส้น",
    "rating": 5,
    "comment": "ทีเด็ดคือหมูแดงอบน้ำผึ้ง หวานกำลังดี นุ่ม ไม่เหนียว ใครมาเมืองตากต้องแวะร้าน ช.สหชัย ครับ",
    "date": "2024-12-12"
  }
]
